unbalancedgw/__init__.py
unbalancedgw/_batch_utils.py
unbalancedgw/_vanilla_utils.py
unbalancedgw/batch_stable_ugw_solver.py
unbalancedgw/utils.py
unbalancedgw/vanilla_ugw_solver.py
unbalancedgw/tests/test_batch_solvers.py
unbalancedgw/tests/test_vanilla_solvers.py
unbalancedgw-0.2.0.dist-info/LICENSE
unbalancedgw-0.2.0.dist-info/METADATA
unbalancedgw-0.2.0.dist-info/WHEEL
unbalancedgw-0.2.0.dist-info/top_level.txt
unbalancedgw-0.2.0.dist-info/RECORD
